django_template_reports-0.5.0.dist-info/licenses/LICENSE
template_reports/__init__.py
template_reports/apps.py
template_reports/default_settings.py
template_reports/dummy_render.py
template_reports/signals.py
template_reports/admin/__init__.py
template_reports/admin/base.py
template_reports/admin/generate.py
template_reports/migrations/0001_initial.py
template_reports/migrations/__init__.py
template_reports/models/__init__.py
template_reports/models/base.py
template_reports/models/default.py
template_reports/models/utils.py
template_reports/templates/admin/choose_report_definition.html
template_reports/templates/admin/configure_report_context.html
template_reports/templates/admin/generate_reports.html
template_reports/templates/admin/report_generation_changelist.html
django_template_reports-0.5.0.dist-info/METADATA
django_template_reports-0.5.0.dist-info/WHEEL
django_template_reports-0.5.0.dist-info/top_level.txt
django_template_reports-0.5.0.dist-info/RECORD
