Metadata-Version: 2.4
Name: django-template-reports
Version: 0.5.0
Summary: Generates reports (PPTX) from template files that are flexibly populated using the Django ORM, without hard-coding.
Project-URL: Homepage, https://github.com/gaussian/django-template-reports
Project-URL: Issues, https://github.com/gaussian/django-template-reports/issues
Requires-Python: >=3.12
License-File: LICENSE
Requires-Dist: Django<6,>=5
Requires-Dist: swapper<2,>=1
Requires-Dist: office-templates>=0.5
Provides-Extra: xlsx
Requires-Dist: office-templates[xlsx]; extra == "xlsx"
Dynamic: license-file
